dvrd_pydate/__init__.py
dvrd_pydate/enums.py
dvrd_pydate/pydate.py
dvrd_pydate/pydatetime.py
dvrd_pydate/tests/__init__.py
dvrd_pydate/tests/test_pydate.py
dvrd_pydate/tests/test_pydatetime.py
dvrd_pydate-1.1.18.dist-info/METADATA
dvrd_pydate-1.1.18.dist-info/WHEEL
dvrd_pydate-1.1.18.dist-info/top_level.txt
dvrd_pydate-1.1.18.dist-info/RECORD
