Metadata-Version: 2.4
Name: dvrd_pydate
Version: 1.1.18
Summary: Python date and datetime extension
Author-email: Dave van Rijn Development <develop@davevanrijn.nl>
Project-URL: Homepage, https://github.com/Dave-van-Rijn-Development/dvrd-pydate.git
Requires-Python: >=3.11
Provides-Extra: test
Requires-Dist: coverage; extra == "test"
